README.md
setup.py
SpryngtimeOpenAI/ChatCompletion.py
SpryngtimeOpenAI/__init__.py
spryngtime_azure_openai_python.egg-info/PKG-INFO
spryngtime_azure_openai_python.egg-info/SOURCES.txt
spryngtime_azure_openai_python.egg-info/dependency_links.txt
spryngtime_azure_openai_python.egg-info/requires.txt
spryngtime_azure_openai_python.egg-info/top_level.txt