Metadata-Version: 2.1
Name: spryngtime-azure-openai-python
Version: 1.0.2
Summary: Spryngtime Usage Analytics & Billing API
Home-page: https://github.com/azianmike/spryngtime-analytics-sdk/tree/main/python
Author: Spryngtime
Author-email: michael@usespryngtime.com
License: MIT
Keywords: Konfig,Spryngtime Usage Analytics & Billing API OpenAI wrapper
Requires-Python: >=3.7
